<!-- vote panel made by nouseforname -->
<manialink id="5"><frame posn="-5 -30 0">
<quad sizen="10 3.5" style="Bgs1InRace" substyle="NavButton" halign="center" action="18" actionkey="1"/>
<label sizen="5 2.5" posn="0 -0.8 2" style="TextButtonSmall" halign="center" text="%YES%"/>
</frame><frame posn="5.5 -30 0">
<quad sizen="10 3.5" style="Bgs1InRace" substyle="NavButton" halign="center" action="19" actionkey="2"/>
<label sizen="5 2.5" posn="0 -0.8 2" style="TextButtonSmall" halign="center" text="%NO%"/>
</frame></manialink>
